{
	"targetRoot" : "https://fmovies.is",
	"search" : "1",
	"searchQuery" : "https://fmovies.is/search?keyword=",
	"searchSeed" : "hobbit",
	"do" :
	[{
		"repeated" : "1",
		"saveThis" : "1",
		"name" : "Posters",
		"afterSequence" : ["poster"],
		"bet"  : "href=\"",
		"ween" : "\"",
		"isThereASubtask" : "1",
		"name":"level1task1",
		"do" : [{
			"taskType":"para",
			"repeated" : "False",
			"name" : "Description",
			"afterSequence" : ["class=\"desc\""],
			"bet"  : ">",
			"ween" : "</",
			"isThereASubtask" : "False"
		}]
	},
	{
		"repeated" : "1",
		"saveThis" : "1",
		"name" : "Posters",
		"afterSequence" : ["poster"],
		"bet"  : "href=\"",
		"ween" : "\"",
		"isThereASubtask" : "1",
		"name":"level1task2",
		"do" : [{
			"taskType":"para",
			"repeated" : "False",
			"name" : "Description",
			"afterSequence" : ["class=\"desc\""],
			"bet"  : ">",
			"ween" : "</",
			"isThereASubtask" : "False"
		}]


	}]
}
